HuizhiwangJiaochengHeji20160914Fix1/README.md
HuizhiwangJiaochengHeji20160914Fix1/__init__.py
HuizhiwangJiaochengHeji20160914Fix1/__main__.py
HuizhiwangJiaochengHeji20160914Fix1/file.epub
HuizhiwangJiaochengHeji20160914Fix1/index.html
HuizhiwangJiaochengHeji20160914Fix1/css/__init__.py
HuizhiwangJiaochengHeji20160914Fix1/css/annotations.css
HuizhiwangJiaochengHeji20160914Fix1/css/main.css
HuizhiwangJiaochengHeji20160914Fix1/css/normalize.css
HuizhiwangJiaochengHeji20160914Fix1/css/popup.css
HuizhiwangJiaochengHeji20160914Fix1/font/__init__.py
HuizhiwangJiaochengHeji20160914Fix1/font/fontello.eot
HuizhiwangJiaochengHeji20160914Fix1/font/fontello.svg
HuizhiwangJiaochengHeji20160914Fix1/font/fontello.ttf
HuizhiwangJiaochengHeji20160914Fix1/font/fontello.woff
HuizhiwangJiaochengHeji20160914Fix1/img/__init__.py
HuizhiwangJiaochengHeji20160914Fix1/img/annotator-glyph-sprite.png
HuizhiwangJiaochengHeji20160914Fix1/img/annotator-icon-sprite.png
HuizhiwangJiaochengHeji20160914Fix1/img/apple-touch-icon.png
HuizhiwangJiaochengHeji20160914Fix1/img/cancelfullscreen.png
HuizhiwangJiaochengHeji20160914Fix1/img/close.png
HuizhiwangJiaochengHeji20160914Fix1/img/fullscreen.png
HuizhiwangJiaochengHeji20160914Fix1/img/loader.gif
HuizhiwangJiaochengHeji20160914Fix1/img/menu-icon.png
HuizhiwangJiaochengHeji20160914Fix1/img/save.png
HuizhiwangJiaochengHeji20160914Fix1/img/saved.png
HuizhiwangJiaochengHeji20160914Fix1/img/settings-s.png
HuizhiwangJiaochengHeji20160914Fix1/img/settings.png
HuizhiwangJiaochengHeji20160914Fix1/img/star.png
HuizhiwangJiaochengHeji20160914Fix1/js/__init__.py
HuizhiwangJiaochengHeji20160914Fix1/js/epub.js
HuizhiwangJiaochengHeji20160914Fix1/js/epub.min.js
HuizhiwangJiaochengHeji20160914Fix1/js/epub.min.map
HuizhiwangJiaochengHeji20160914Fix1/js/hooks.min.js
HuizhiwangJiaochengHeji20160914Fix1/js/hooks.min.map
HuizhiwangJiaochengHeji20160914Fix1/js/reader.js
HuizhiwangJiaochengHeji20160914Fix1/js/reader.js.map
HuizhiwangJiaochengHeji20160914Fix1/js/reader.min.js
huizhiwang_jiaocheng_heji_20160914_fix1-2024.3.1.0.dist-info/METADATA
huizhiwang_jiaocheng_heji_20160914_fix1-2024.3.1.0.dist-info/WHEEL
huizhiwang_jiaocheng_heji_20160914_fix1-2024.3.1.0.dist-info/entry_points.txt
huizhiwang_jiaocheng_heji_20160914_fix1-2024.3.1.0.dist-info/top_level.txt
huizhiwang_jiaocheng_heji_20160914_fix1-2024.3.1.0.dist-info/RECORD
